fds/__init__.py
fds/sdk/__init__.py
fds/sdk/Portfolio/__init__.py
fds/sdk/Portfolio/api_client.py
fds/sdk/Portfolio/configuration.py
fds/sdk/Portfolio/exceptions.py
fds/sdk/Portfolio/model_utils.py
fds/sdk/Portfolio/rest.py
fds/sdk/Portfolio/api/__init__.py
fds/sdk/Portfolio/api/model_accounts_api.py
fds/sdk/Portfolio/apis/__init__.py
fds/sdk/Portfolio/model/__init__.py
fds/sdk/Portfolio/model/client_error_response.py
fds/sdk/Portfolio/model/data_and_meta_model.py
fds/sdk/Portfolio/model/error.py
fds/sdk/Portfolio/model/error_source.py
fds/sdk/Portfolio/model/model_account_additional_field.py
fds/sdk/Portfolio/model/model_account_fields.py
fds/sdk/Portfolio/model/model_account_fields_root.py
fds/sdk/Portfolio/model/model_account_schema_root.py
fds/sdk/Portfolio/models/__init__.py
fds.sdk.Portfolio-1.0.1.dist-info/LICENSE
fds.sdk.Portfolio-1.0.1.dist-info/METADATA
fds.sdk.Portfolio-1.0.1.dist-info/WHEEL
fds.sdk.Portfolio-1.0.1.dist-info/top_level.txt
fds.sdk.Portfolio-1.0.1.dist-info/RECORD
